<?xml version="1.0" encoding="utf-8" ?>
<products>
  <product>
    <name>Code Complete</name>
    <price>50</price>
    <description>Code Complete - Melhor livro sobre desenvolvimento de software</description>
    <quantity>1</quantity>
    <image>http://ecx.images-amazon.com/images/I/51nWkLCu1SL._SS500_.jpg</image>
  </product>
  <product>
    <name>How We Test Software at Microsoft</name>
    <price>50</price>
    <description></description>
    <quantity>1</quantity>
    <image>http://blogs.msdn.com/blogfiles/imtesty/WindowsLiveWriter/HowWeTestSoftwareAtMicrosoft_9FA9/hwtsams_2.jpg</image>
  </product>
  <product>
    <name>Refactoring</name>
    <price>60</price>
    <description></description>
    <quantity>1</quantity>
    <image>http://martinfowler.com/refactoringBook.jpg</image>
  </product>
  <product>
    <name>Engenharia de Software</name>
    <price>80</price>
    <description></description>
    <quantity>1</quantity>
    <image>http://www.livrariaresposta.com.br/fotos/9788588639287.jpg</image>
  </product>
  <product>
    <name>Utilizando UML e Padrões</name>
    <price>80</price>
    <description></description>
    <quantity>1</quantity>
    <image>http://i.s8.com.br/images/books/cover/img2/158382_4.jpg</image>
  </product>
  <product>
    <name>Linux - Só por Prazer</name>
    <price>30</price>
    <description></description>
    <quantity>1</quantity>
    <image>http://skoob.s3.amazonaws.com/livros/17661/LINUX__SO_POR_PRAZER__1238796215P.jpg</image>
  </product>
  <product>
    <name>Competindo pelo Futuro</name>
    <price>30</price>
    <description></description>
    <quantity>1</quantity>
    <image>http://i.s8.com.br/images/books/cover/img8/290048_4.jpg</image>
  </product>
  <product>
    <name>What's Science Ever Done For Us</name>
    <price>20</price>
    <description>What's Science Ever Done For Us: What the Simpsons Can Teach Us About Physics, Robots, Life, and the Universe</description>
    <quantity>1</quantity>
    <image>http://pdfcast.org/images/aff/9780470169513.jpg</image>
  </product>
  <product>
    <name>What they don't teach you at Harvard Business School</name>
    <price>10</price>
    <description></description>
    <quantity>1</quantity>
    <image>http://images.betterworldbooks.com/055/What-They-Don-t-Teach-You-at-Harvard-Business-School-9780553345834.jpg</image>
  </product>
  <product>
    <name>Freakonomics</name>
    <price>20</price>
    <description>Freakonomics: o Lado Oculto e Inesperado de Tudo que nos Afeta</description>
    <quantity>1</quantity>
    <image>http://imagex.buscape.com.br/capas/livros/704/227/200x200_8535227407.jpg</image>
  </product>
  <product>
    <name>O Universo Numa Casca de Noz</name>
    <price>20</price>
    <description></description>
    <quantity>1</quantity>
    <image>http://imagex.buscape.com.br/capas/livros/987/926/200x200_8520926789.jpg</image>
  </product>
  <product>
    <name>Start Up</name>
    <price>15</price>
    <description></description>
    <quantity>1</quantity>
    <image>http://imagex.buscape.com.br/capas/livros/549/009/200x200_8522009945.jpg</image>
  </product>
  <product>
    <name>Segurança Total</name>
    <price>10</price>
    <description>Seguranca Total - Protegendo-se Contra os Hackers</description>
    <quantity>1</quantity>
    <image>http://imagex.buscape.com.br/capas/livros/886/611/200x200_8534611688.jpg</image>
  </product>
  <product>
    <name>Manual Completo do Hacker</name>
    <price>10</price>
    <description>Manual Completo do Hacker Como Ser e Evitá-los</description>
    <quantity>1</quantity>
    <image>http://imagex.buscape.com.br/capas/livros/197/846/200x200_8586846791.jpg</image>
  </product>
  <product>
    <name>The Accidental Billionaires</name>
    <price>20</price>
    <description></description>
    <quantity>1</quantity>
    <image>http://imagex.buscape.com.br/capas/livros/055/019/200x200_0434019550.jpg</image>
  </product>
  

</products>
